wmul_logger/__init__.py
wmul_logger/logger.py
wmul_logger-0.6.0.dist-info/LICENSE
wmul_logger-0.6.0.dist-info/WHEEL
wmul_logger-0.6.0.dist-info/METADATA
wmul_logger-0.6.0.dist-info/RECORD
